changyong/__init__.py
changyong-1.0.5.dist-info/METADATA
changyong-1.0.5.dist-info/WHEEL
changyong-1.0.5.dist-info/top_level.txt
changyong-1.0.5.dist-info/RECORD
